txtferret/__init__.py
txtferret/_config.py
txtferret/_default.py
txtferret/_sanity.py
txtferret/cli.py
txtferret/core.py
txtferret-0.3.2.dist-info/LICENSE
txtferret-0.3.2.dist-info/METADATA
txtferret-0.3.2.dist-info/WHEEL
txtferret-0.3.2.dist-info/entry_points.txt
txtferret-0.3.2.dist-info/top_level.txt
txtferret-0.3.2.dist-info/RECORD
