Metadata-Version: 2.1
Name: txtferret
Version: 0.3.2
Summary: Scan text files for sensitive (or non-sensitive) data.
Home-page: https://github.com/krayzpipes/txt-ferret
Author: Kyle Piper
Author-email: kylepiper29@gmail.com
License: License :: OSI Approved :: Apache Software License
Keywords: pci,dlp,text,scan,regex
Platform: UNKNOWN
Classifier: Development Status :: 4 - Beta
Classifier: Intended Audience :: Information Technology
Classifier: Intended Audience :: Financial and Insurance Industry
Classifier: Intended Audience :: System Administrators
Classifier: Operating System :: OS Independent
Classifier: Topic :: Security
Classifier: License :: OSI Approved :: Apache Software License
Classifier: Programming Language :: Python :: 3 :: Only
Classifier: Programming Language :: Python :: 3.6
Classifier: Programming Language :: Python :: 3.7
Requires-Dist: click
Requires-Dist: loguru
Requires-Dist: pyyaml
